Metadata-Version: 2.1
Name: ippanel
Version: 1.1.0
Summary: ippanel sdk
Home-page: https://github.com/ippanel/python-rest-sdk
Author: Asghar Dadashzadeh
Author-email: dev@ippanel.com
License: BSD-2-Clause
Platform: UNKNOWN
Classifier: Programming Language :: Python
Classifier: Programming Language :: Python :: 2
Classifier: Programming Language :: Python :: 3
